[
  {
    "titulo": "Petróleo fecha em alta após Trump elevar o tom de vingança contra Irã",
    "link": "https://www.infomoney.com.br/mercados/petroleo-abertura-fechamento-ira-eua-20072026/",
    "imagem": "https://www.infomoney.com.br/wp-content/uploads/2026/04/Guerra-Petroleo.jpg?fit=300%2C169&amp;quality=70&amp;strip=all",
    "fonte": "InfoMoney (geral)",
    "publicado_em": "Mon, 20 Jul 2026 19:46:53 +0000"
  },
  {
    "titulo": "FII investe R$ 26,1 milhões para assumir 100% de parque logístico em Guarulhos",
    "link": "https://www.infomoney.com.br/onde-investir/fii-investe-r-261-milhoes-para-assumir-100-de-parque-logistico-em-guarulhos/",
    "imagem": "https://www.infomoney.com.br/wp-content/uploads/2026/07/Captura-de-Tela-2026-07-20-as-16.40.51.png?fit=300%2C119&amp;quality=70&amp;strip=all",
    "fonte": "InfoMoney (geral)",
    "publicado_em": "Mon, 20 Jul 2026 19:45:36 +0000"
  },
  {
    "titulo": "Escalada da guerra expõe fracasso do acordo entre Irã e EUA",
    "link": "https://www.infomoney.com.br/mundo/escalada-da-guerra-expoe-fracasso-do-acordo-entre-ira-e-eua/",
    "imagem": "https://www.infomoney.com.br/wp-content/uploads/2026/07/ataque-eua-iran-guerra-hormuz-01.jpg?fit=300%2C191&amp;quality=70&amp;strip=all",
    "fonte": "InfoMoney (geral)",
    "publicado_em": "Mon, 20 Jul 2026 19:37:30 +0000"
  }
]